tci/__init__.py
tci/dict.py
tci-0.1.2.dist-info/DESCRIPTION.rst
tci-0.1.2.dist-info/METADATA
tci-0.1.2.dist-info/RECORD
tci-0.1.2.dist-info/WHEEL
tci-0.1.2.dist-info/entry_points.txt
tci-0.1.2.dist-info/metadata.json
tci-0.1.2.dist-info/top_level.txt
tci-0.1.2.dist-info/zip-safe
